{
    "version": "https://jsonfeed.org/version/1",
    "title": "istok.pw",
    "description": "",
    "home_page_url": "https://istok.pw",
    "feed_url": "https://istok.pw/feed.json",
    "user_comment": "",
    "author": {
        "name": "Evgeny Nikiforov"
    },
    "items": [
        {
            "id": "https://istok.pw/ooo-lesslessistokgreatergreater.html",
            "url": "https://istok.pw/ooo-lesslessistokgreatergreater.html",
            "title": "ООО «ИСТОК»",
            "summary": "ООО «ИСТОК» образовано в 2009 г. специалистами по преобразовательной технике. Наше предприятие занимается разработкой, изготовлением и поставкой аппаратуры регулирования и контроля (АРК) для автономных систем&hellip;",
            "content_html": "<p>ООО «ИСТОК» образовано в 2009 г. специалистами по преобразовательной технике.</p>\n<p>Наше предприятие занимается разработкой, изготовлением и поставкой аппаратуры регулирования и контроля (АРК) для автономных систем электроснабжения (СЭС) различного, в том числе специального назначения с использованием альтернативных и перспективных генераторов и накопителей энергии различных типов (фотоэлектрических преобразователей, литий-ионных аккумуляторов, ионисторов – «суперконденсаторов» и т.д.). Формируем структуры систем, обеспечиваем оптимальное согласование характеристик генераторов, накопителей и потребителей электроэнергии для заданных условий эксплуатации СЭС, рассчитываем энергобаланс, комплектуем системы необходимой АРК, в том числе сервисными устройствами нашей разработки.</p>",
            "author": {
                "name": "Evgeny Nikiforov"
            },
            "tags": [
            ],
            "date_published": "2021-09-17T22:44:44+03:00",
            "date_modified": "2021-09-17T22:47:18+03:00"
        }
    ]
}
